MANIFEST.in
README
setup.cfg
setup.py
eaftest/__init__.py
eaftest/bintools.py
eaftest/cmd.py
eaftest/datasets.py
eaftest/eaf_test_kreduce.py
eaftest/eaf_test_kscoarse.py
eaftest/eaf_test_ksfine.py
eaftest.egg-info/PKG-INFO
eaftest.egg-info/SOURCES.txt
eaftest.egg-info/dependency_links.txt
eaftest.egg-info/entry_points.txt
eaftest.egg-info/not-zip-safe
eaftest.egg-info/requires.txt
eaftest.egg-info/top_level.txt
eaftest/clkernels/__init__.py
eaftest/clkernels/reduce4-xor.cl
eaftest/clkernels/reduce4.cl
eaftest/clkernels/square-3-xor-parted-fine.cl
eaftest/clkernels/square-3-xor-parted.cl
eaftest/libaft/Makefile
eaftest/libaft/README
eaftest/libaft/__init__.py
eaftest/libaft/eaf2d.c
eaftest/libaft/eaftest.c
eaftest/libeafbb/Makefile
eaftest/libeafbb/__init__.py
eaftest/libeafbb/algorithm.c
eaftest/libeafbb/algorithm.h
eaftest/libeafbb/dataload.c
eaftest/libeafbb/dataload.h
eaftest/libeafbb/eafbb.c
eaftest/libeafbb/eafbb.h
eaftest/libeafbb/heuristic.c
eaftest/libeafbb/heuristic.h
eaftest/libeafbb/main.c
eaftest/utils/__init__.py
eaftest/utils/py3k.py