Metadata-Version: 1.1
Name: eaftest
Version: 0.1.dev5
Summary: Tools to perform hypothesis tests based on the empirical attainment function.
Home-page: https://bitbucket.org/hjalves/eaftest
Author: Humberto Alves
Author-email: halves@uc.pt
License: GPL
Keywords: eaf statistics opencl
Platform: UNKNOWN
Classifier: Development Status :: 2 - Pre-Alpha
Classifier: Environment :: Console
Classifier: Intended Audience :: Science/Research
Classifier: License :: OSI Approved :: GNU General Public License v2 (GPLv2)
Classifier: Operating System :: POSIX :: Linux
Classifier: Programming Language :: Python :: 2.7
Classifier: Topic :: Scientific/Engineering
